{
  "pages": [{
      "path": "pages/index/index",
      "style": {
        "navigationStyle": "custom"
      }
    },
    {
      "path": "pages/index/search",
      "style": {
        "navigationBarTitleText": "搜索活动"
      }
    },
    {
      "path": "pages/index/detail",
      "style": {
        "navigationBarTitleText": "活动详情"
      }
    },
    {
      "path": "pages/add/dynamic",
      "style": {
        "navigationBarTitleText": "发布动态"
      }
    },
    {
      "path": "pages/add/activity",
      "style": {
        "navigationBarTitleText": "发布活动"
      }
    },
    {
      "path": "pages/me/me",
      "style": {
        "navigationStyle": "custom"
      }
    },
    {
      "path" : "pages/dynamic/dynamic",
      "style" : 
      {
        "navigationBarTitleText": "动态"
      }
    },
    {
      "path" : "pages/message/message",
      "style" : 
      {
        "navigationBarTitleText": "消息"
      }
    },
	{
	  "path" : "pages/message/chat-window",
	  "style" : 
	  {
	    "navigationStyle": "custom"
	  }
	},
  {
    "path" : "pages/message/add-friend",
    "style" : 
    {
      "navigationBarTitleText": "添加好友"
    }
  },
  {
    "path" : "pages/me/info-manage",
     "style" : 
     {
       "navigationBarTitleText": "个人信息管理"
     }
  },
  {
    "path" : "pages/me/friend-manage",
     "style" : 
     {
       "navigationBarTitleText": "好友管理"
     }
  },
  {
    "path" : "pages/me/my-published",
    "style" : 
    {
      "navigationBarTitleText": "我发布的活动"
    }
  },
  {
    "path" : "pages/me/my-joined",
    "style" : 
    {
      "navigationBarTitleText": "我参加的活动"
    }
  },
  {
    "path" : "pages/me/feedback",
    "style" : 
    {
      "navigationBarTitleText": "反馈"
    }
  },
  {
    "path" : "pages/me/about",
    "style" : 
    {
      "navigationBarTitleText": "关于"
    }
  }
  ],
  "globalStyle": {
    "navigationBarTextStyle": "black",
    "navigationBarTitleText": "有缘U伴",
    "navigationBarBackgroundColor": "#F8F8F8",
    "backgroundColor": "#F8F8F8",
    "app-plus": {
      "background": "#efeff4"
    }
  }
}